{
  "collections": [
    {
      "id": "amazon_productivity",
      "slug": "amazon-productivity",
      "product_count": 5,
      "top_products": [
        "standing_desk_converter",
        "blue_light_glasses",
        "am_7ddca06356da",
        "am_065326f51f74",
        "am_81950e2037dc"
      ],
      "url": "https://perth-hang-pair-acceptance.trycloudflare.com/collection-amazon_productivity.html"
    },
    {
      "id": "family_fashion",
      "slug": "family-fashion",
      "product_count": 37,
      "top_products": [
        "am_a394427f1557",
        "am_43b5e4aa2e36",
        "am_e0cfd8e2aa23",
        "am_579581370f40",
        "am_f029cae26979",
        "am_9ed7a6a589ce",
        "am_988bba45449d",
        "am_aee719fe39cc",
        "am_2bf98c1669b1",
        "am_c67ea71bdeac"
      ],
      "url": "https://perth-hang-pair-acceptance.trycloudflare.com/collection-family_fashion.html"
    },
    {
      "id": "anime_collectibles",
      "slug": "anime-collectibles",
      "product_count": 17,
      "top_products": [
        "am_e1b70ea122c3",
        "am_08aa3cbb043b",
        "am_580001b4a5dc",
        "am_0949ec41e7a3",
        "am_f21756501f6b",
        "am_ea89f4677813",
        "am_102102c90dc3",
        "am_7063167a2bea",
        "am_41b008043a33",
        "am_e6d26f084692"
      ],
      "url": "https://perth-hang-pair-acceptance.trycloudflare.com/collection-anime_collectibles.html"
    },
    {
      "id": "fashion_shoes",
      "slug": "fashion-shoes",
      "product_count": 16,
      "top_products": [
        "am_96bb5eccb127",
        "am_28c12ff4b3bc",
        "am_70dc65c3b842",
        "am_b1a628cf7694",
        "am_1b2f84b84988",
        "am_63ce97cd6d52",
        "am_f3b0319496d2",
        "am_e7ea3dcdf7b4",
        "am_ee0e3bfbe296",
        "am_c751ef10c842"
      ],
      "url": "https://perth-hang-pair-acceptance.trycloudflare.com/collection-fashion_shoes.html"
    },
    {
      "id": "home_decor",
      "slug": "home-decor",
      "product_count": 55,
      "top_products": [
        "am_e20476103c21",
        "am_dbf057427bcb",
        "am_e7b2e4207b55",
        "am_9f2dffacb000",
        "am_5dbf26879b9b",
        "am_d8d41feab7a7",
        "am_af0e72ed36f8",
        "am_dc83c8acce6e",
        "am_2c23668629d3",
        "am_498ff6f54f2b"
      ],
      "url": "https://perth-hang-pair-acceptance.trycloudflare.com/collection-home_decor.html"
    },
    {
      "id": "toys_gadgets",
      "slug": "toys-gadgets",
      "product_count": 32,
      "top_products": [
        "am_fb8a3eb38669",
        "am_130362a518ce",
        "am_2156c8dc3d35",
        "am_6b7be9b74dfc",
        "am_a03aff7f003c",
        "am_0034d98f69fa",
        "am_1c0799d928f6",
        "am_7430087ef58e",
        "am_4d03711e3a52",
        "am_4be9b657d0fb"
      ],
      "url": "https://perth-hang-pair-acceptance.trycloudflare.com/collection-toys_gadgets.html"
    },
    {
      "id": "amazon_home",
      "slug": "amazon-home",
      "product_count": 40,
      "top_products": [
        "am_37779f1b2e1a",
        "am_2e3839d394ae",
        "am_1ad9d1b2d5e3",
        "closet_organizer",
        "storage_box_system",
        "under_sink_organizer",
        "am_4547121d38e6",
        "am_8c82c16eb273",
        "am_a0e8307b1ee5",
        "am_d8f09fde7416"
      ],
      "url": "https://perth-hang-pair-acceptance.trycloudflare.com/collection-amazon_home.html"
    },
    {
      "id": "home_improvement",
      "slug": "home-improvement",
      "product_count": 38,
      "top_products": [
        "am_5f8f9a3b4839",
        "am_b002bdfb1070",
        "am_98e89ef2f6da",
        "am_ea96159f85a8",
        "am_b89d86a08618",
        "am_648feef675d9",
        "am_f3173624c712",
        "am_d7b889f40881",
        "am_310212aa63c0",
        "am_c050c6783187"
      ],
      "url": "https://perth-hang-pair-acceptance.trycloudflare.com/collection-home_improvement.html"
    },
    {
      "id": "amazon_tech",
      "slug": "amazon-tech",
      "product_count": 52,
      "top_products": [
        "am_c314091296e4",
        "al_c09646193f43",
        "am_fdde294b0fed",
        "wireless_earbuds",
        "am_422a9b3068d9",
        "am_49a1b4fbd310",
        "am_db8bb50870c0",
        "am_522fa27630f5",
        "am_ac21e9d2fc42",
        "am_9b7c755a8510"
      ],
      "url": "https://perth-hang-pair-acceptance.trycloudflare.com/collection-amazon_tech.html"
    },
    {
      "id": "home_electronics",
      "slug": "home-electronics",
      "product_count": 48,
      "top_products": [
        "am_a2020de2a18a",
        "am_7efb4959536c",
        "am_6afa0dc38348",
        "am_24250eb7bbd0",
        "am_2d667cddb6f7",
        "am_0c337c851e4a",
        "am_ddba6c165b08",
        "am_9f34d22ce489",
        "am_0550f36c4b02",
        "am_a7dd07c6d618"
      ],
      "url": "https://perth-hang-pair-acceptance.trycloudflare.com/collection-home_electronics.html"
    },
    {
      "id": "amazon_car",
      "slug": "amazon-car",
      "product_count": 21,
      "top_products": [
        "am_24d633732ddb",
        "car_phone_mount",
        "portable_car_vacuum",
        "am_06ad5832c84e",
        "am_dc1dcf3cbe8b",
        "am_27c042651a33",
        "am_abd254ee8532",
        "am_c74ae971261b",
        "am_795331ded27f",
        "am_ed0711637191"
      ],
      "url": "https://perth-hang-pair-acceptance.trycloudflare.com/collection-amazon_car.html"
    },
    {
      "id": "amazon_sleep",
      "slug": "amazon-sleep",
      "product_count": 1,
      "top_products": [
        "am_eb20045bd5e4"
      ],
      "url": "https://perth-hang-pair-acceptance.trycloudflare.com/collection-amazon_sleep.html"
    },
    {
      "id": "outdoor_gear",
      "slug": "outdoor-gear",
      "product_count": 3,
      "top_products": [
        "am_cf4f97758d6e",
        "am_3134fbffe62c",
        "am_56993caf408f"
      ],
      "url": "https://perth-hang-pair-acceptance.trycloudflare.com/collection-outdoor_gear.html"
    },
    {
      "id": "amazon_beauty",
      "slug": "amazon-beauty",
      "product_count": 4,
      "top_products": [
        "hair_curler_auto",
        "led_face_mask",
        "facial_cleansing_brush",
        "am_355df8aa7f5a"
      ],
      "url": "https://perth-hang-pair-acceptance.trycloudflare.com/collection-amazon_beauty.html"
    },
    {
      "id": "amazon_kitchen",
      "slug": "amazon-kitchen",
      "product_count": 14,
      "top_products": [
        "vegetable_chopper",
        "meal_prep_containers",
        "air_fryer",
        "am_e9e4fa35fbca",
        "am_c793b8ba44e2",
        "am_d0258accf23d",
        "am_4640d74da337",
        "am_384941aec1e0",
        "am_309e9194075f",
        "am_b1b6eabc2f68"
      ],
      "url": "https://perth-hang-pair-acceptance.trycloudflare.com/collection-amazon_kitchen.html"
    },
    {
      "id": "amazon_travel",
      "slug": "amazon-travel",
      "product_count": 4,
      "top_products": [
        "packing_cubes",
        "travel_backpack",
        "am_d5b7ba29d825",
        "am_bd0fd95bb448"
      ],
      "url": "https://perth-hang-pair-acceptance.trycloudflare.com/collection-amazon_travel.html"
    },
    {
      "id": "home_wellness",
      "slug": "home-wellness",
      "product_count": 32,
      "top_products": [
        "am_178f93e159e5",
        "am_4e03d2964e29",
        "am_a4384ced4e57",
        "am_d71b46e3a7f8",
        "am_84ff84fa7fe7",
        "am_0f3e9960c588",
        "am_298f8d0e0859",
        "am_fbe5fbe0a3ef",
        "am_2c1cf546b989",
        "am_5c5af290066a"
      ],
      "url": "https://perth-hang-pair-acceptance.trycloudflare.com/collection-home_wellness.html"
    },
    {
      "id": "home_appliances",
      "slug": "home-appliances",
      "product_count": 4,
      "top_products": [
        "am_cfcd34b17b1b",
        "am_d189214ff69a",
        "am_f1b67f2716ac",
        "am_c394f72700ce"
      ],
      "url": "https://perth-hang-pair-acceptance.trycloudflare.com/collection-home_appliances.html"
    },
    {
      "id": "sports_shoes",
      "slug": "sports-shoes",
      "product_count": 5,
      "top_products": [
        "am_b9d5b28c5e8b",
        "am_51bfe36bd227",
        "am_3817fa47700e",
        "am_9f6ae3a8300a",
        "am_40a096273734"
      ],
      "url": "https://perth-hang-pair-acceptance.trycloudflare.com/collection-sports_shoes.html"
    },
    {
      "id": "grooming_tools",
      "slug": "grooming-tools",
      "product_count": 5,
      "top_products": [
        "am_0d09bd56442a",
        "am_3b0938d060af",
        "am_7ebfd3c95391",
        "am_1fd9d625a09b",
        "am_0ea0f8df692b"
      ],
      "url": "https://perth-hang-pair-acceptance.trycloudflare.com/collection-grooming_tools.html"
    },
    {
      "id": "amazon_fitness",
      "slug": "amazon-fitness",
      "product_count": 9,
      "top_products": [
        "jump_rope_pro",
        "resistance_bands",
        "adjustable_dumbbells",
        "am_71ad5451f294",
        "am_9dc3bff3adc2",
        "am_064d92a719a3",
        "am_7683b05210d1",
        "am_ad9582f81957",
        "am_d8bef40ce5d3"
      ],
      "url": "https://perth-hang-pair-acceptance.trycloudflare.com/collection-amazon_fitness.html"
    },
    {
      "id": "amazon_pets",
      "slug": "amazon-pets",
      "product_count": 12,
      "top_products": [
        "auto_pet_feeder",
        "dog_training_collar",
        "al_464ec6bdaff3",
        "am_7445062d94d1",
        "am_861524f2d6d2",
        "am_38a7da52c397",
        "am_c920444c5c7a",
        "am_9d96f9294f6d",
        "am_bed0d32fd735",
        "al_5ad557498ee4"
      ],
      "url": "https://perth-hang-pair-acceptance.trycloudflare.com/collection-amazon_pets.html"
    },
    {
      "id": "amazon_creator",
      "slug": "amazon-creator",
      "product_count": 5,
      "top_products": [
        "ring_light",
        "phone_tripod",
        "am_c400cb8fb42a",
        "am_935eb48f9813",
        "am_d84394acd958"
      ],
      "url": "https://perth-hang-pair-acceptance.trycloudflare.com/collection-amazon_creator.html"
    },
    {
      "id": "amazon_soccer",
      "slug": "amazon-soccer",
      "product_count": 5,
      "top_products": [
        "soccer_training_cones",
        "soccer_rebounder",
        "agility_ladder",
        "am_771c0a9bc7e2",
        "am_0cc6aeb01f2e"
      ],
      "url": "https://perth-hang-pair-acceptance.trycloudflare.com/collection-amazon_soccer.html"
    },
    {
      "id": "aliexpress_deals",
      "slug": "aliexpress-deals",
      "product_count": 2,
      "top_products": [
        "am_14c61a92db83",
        "am_0e78b8c1c38f"
      ],
      "url": "https://perth-hang-pair-acceptance.trycloudflare.com/collection-aliexpress_deals.html"
    },
    {
      "id": "electronics_audio",
      "slug": "electronics-audio",
      "product_count": 14,
      "top_products": [
        "am_54bc11548c56",
        "am_d008ab4835b3",
        "am_afd11890e127",
        "am_73b615410253",
        "am_79e0801a544e",
        "am_dabcb95578e0",
        "am_e3f1d3c1cd9c",
        "am_dadc929dc31f",
        "am_71eb0cb867c9",
        "am_a8e17419fff0"
      ],
      "url": "https://perth-hang-pair-acceptance.trycloudflare.com/collection-electronics_audio.html"
    },
    {
      "id": "beauty_wigs",
      "slug": "beauty-wigs",
      "product_count": 2,
      "top_products": [
        "am_f1b99218dc1e",
        "am_93dd48931efe"
      ],
      "url": "https://perth-hang-pair-acceptance.trycloudflare.com/collection-beauty_wigs.html"
    },
    {
      "id": "beauty_skincare",
      "slug": "beauty-skincare",
      "product_count": 1,
      "top_products": [
        "am_6765cacbc615"
      ],
      "url": "https://perth-hang-pair-acceptance.trycloudflare.com/collection-beauty_skincare.html"
    },
    {
      "id": "jewelry",
      "slug": "jewelry",
      "product_count": 7,
      "top_products": [
        "am_ab98aef64af1",
        "am_34193be2438c",
        "am_6367fbf04ec5",
        "am_5520821cb195",
        "am_3a89cbe089a7",
        "am_5a48eb610e2c",
        "am_f9c083fc7764"
      ],
      "url": "https://perth-hang-pair-acceptance.trycloudflare.com/collection-jewelry.html"
    },
    {
      "id": "fragrance",
      "slug": "fragrance",
      "product_count": 3,
      "top_products": [
        "am_126b80114e49",
        "am_eaccd62a49aa",
        "am_e90b117e5eb2"
      ],
      "url": "https://perth-hang-pair-acceptance.trycloudflare.com/collection-fragrance.html"
    },
    {
      "id": "beauty_grooming",
      "slug": "beauty-grooming",
      "product_count": 2,
      "top_products": [
        "am_5d4010d9327c",
        "am_bd6485f4c2dc"
      ],
      "url": "https://perth-hang-pair-acceptance.trycloudflare.com/collection-beauty_grooming.html"
    },
    {
      "id": "fitness_wellness",
      "slug": "fitness-wellness",
      "product_count": 2,
      "top_products": [
        "am_ecc1aa7810bd",
        "am_3700ecdcfd1a"
      ],
      "url": "https://perth-hang-pair-acceptance.trycloudflare.com/collection-fitness_wellness.html"
    },
    {
      "id": "car_accessories",
      "slug": "car-accessories",
      "product_count": 1,
      "top_products": [
        "am_9efb0b0c8d9a"
      ],
      "url": "https://perth-hang-pair-acceptance.trycloudflare.com/collection-car_accessories.html"
    },
    {
      "id": "garden_tools",
      "slug": "garden-tools",
      "product_count": 1,
      "top_products": [
        "am_81496142ed14"
      ],
      "url": "https://perth-hang-pair-acceptance.trycloudflare.com/collection-garden_tools.html"
    },
    {
      "id": "home_textiles",
      "slug": "home-textiles",
      "product_count": 1,
      "top_products": [
        "am_5bfe6d4032c3"
      ],
      "url": "https://perth-hang-pair-acceptance.trycloudflare.com/collection-home_textiles.html"
    }
  ]
}