{
  "collections": [
    {
      "id": "amazon_productivity",
      "slug": "amazon-productivity",
      "product_count": 2,
      "top_products": [
        "standing_desk_converter",
        "blue_light_glasses"
      ],
      "url": "https://aware-wine-analyzed-transcripts.trycloudflare.com/collection-amazon_productivity.html"
    },
    {
      "id": "amazon_beauty",
      "slug": "amazon-beauty",
      "product_count": 3,
      "top_products": [
        "facial_cleansing_brush",
        "hair_curler_auto",
        "led_face_mask"
      ],
      "url": "https://aware-wine-analyzed-transcripts.trycloudflare.com/collection-amazon_beauty.html"
    },
    {
      "id": "amazon_kitchen",
      "slug": "amazon-kitchen",
      "product_count": 3,
      "top_products": [
        "vegetable_chopper",
        "air_fryer",
        "meal_prep_containers"
      ],
      "url": "https://aware-wine-analyzed-transcripts.trycloudflare.com/collection-amazon_kitchen.html"
    },
    {
      "id": "amazon_travel",
      "slug": "amazon-travel",
      "product_count": 2,
      "top_products": [
        "packing_cubes",
        "travel_backpack"
      ],
      "url": "https://aware-wine-analyzed-transcripts.trycloudflare.com/collection-amazon_travel.html"
    },
    {
      "id": "amazon_fitness",
      "slug": "amazon-fitness",
      "product_count": 3,
      "top_products": [
        "jump_rope_pro",
        "adjustable_dumbbells",
        "resistance_bands"
      ],
      "url": "https://aware-wine-analyzed-transcripts.trycloudflare.com/collection-amazon_fitness.html"
    },
    {
      "id": "amazon_pets",
      "slug": "amazon-pets",
      "product_count": 2,
      "top_products": [
        "dog_training_collar",
        "auto_pet_feeder"
      ],
      "url": "https://aware-wine-analyzed-transcripts.trycloudflare.com/collection-amazon_pets.html"
    },
    {
      "id": "amazon_creator",
      "slug": "amazon-creator",
      "product_count": 2,
      "top_products": [
        "phone_tripod",
        "ring_light"
      ],
      "url": "https://aware-wine-analyzed-transcripts.trycloudflare.com/collection-amazon_creator.html"
    },
    {
      "id": "amazon_tech",
      "slug": "amazon-tech",
      "product_count": 1,
      "top_products": [
        "wireless_earbuds"
      ],
      "url": "https://aware-wine-analyzed-transcripts.trycloudflare.com/collection-amazon_tech.html"
    },
    {
      "id": "amazon_soccer",
      "slug": "amazon-soccer",
      "product_count": 3,
      "top_products": [
        "soccer_training_cones",
        "soccer_rebounder",
        "agility_ladder"
      ],
      "url": "https://aware-wine-analyzed-transcripts.trycloudflare.com/collection-amazon_soccer.html"
    },
    {
      "id": "amazon_home",
      "slug": "amazon-home",
      "product_count": 3,
      "top_products": [
        "closet_organizer",
        "under_sink_organizer",
        "storage_box_system"
      ],
      "url": "https://aware-wine-analyzed-transcripts.trycloudflare.com/collection-amazon_home.html"
    },
    {
      "id": "amazon_car",
      "slug": "amazon-car",
      "product_count": 2,
      "top_products": [
        "car_phone_mount",
        "portable_car_vacuum"
      ],
      "url": "https://aware-wine-analyzed-transcripts.trycloudflare.com/collection-amazon_car.html"
    }
  ]
}